jupyter_cell_extractor/__init__.py
jupyter_cell_extractor/data/classic.tplx
jupyter_cell_extractor/data/treeguide.txt
jupyter_cell_extractor/main.py
jupyter_cell_extractor-1.0.0.dist-info/WHEEL
jupyter_cell_extractor-1.0.0.dist-info/METADATA
jupyter_cell_extractor-1.0.0.dist-info/RECORD
